setup.py
frasco_facebook/__init__.py
frasco_facebook/blueprint.py
frasco_facebook.egg-info/PKG-INFO
frasco_facebook.egg-info/SOURCES.txt
frasco_facebook.egg-info/dependency_links.txt
frasco_facebook.egg-info/not-zip-safe
frasco_facebook.egg-info/requires.txt
frasco_facebook.egg-info/top_level.txt