Metadata-Version: 1.0
Name: frasco-facebook
Version: 0.1
Summary: Facebook integration for Frasco
Home-page: http://github.com/frascoweb/frasco-facebook
Author: Maxime Bouroumeau-Fuseau
Author-email: maxime.bouroumeau@gmail.com
License: MIT
Platform: any
